sphinxcontrib_astah-1.0.0-py2.7-nspkg.pth
sphinxcontrib/astah.py
sphinxcontrib_astah-1.0.0.dist-info/DESCRIPTION.rst
sphinxcontrib_astah-1.0.0.dist-info/METADATA
sphinxcontrib_astah-1.0.0.dist-info/metadata.json
sphinxcontrib_astah-1.0.0.dist-info/namespace_packages.txt
sphinxcontrib_astah-1.0.0.dist-info/RECORD
sphinxcontrib_astah-1.0.0.dist-info/top_level.txt
sphinxcontrib_astah-1.0.0.dist-info/WHEEL
