Metadata-Version: 2.0
Name: sphinxcontrib-astah
Version: 1.0.0
Summary: Sphinx "astah" extension; embed diagram by using astah
Home-page: https://github.com/tk0miya/sphinxcontrib-astah
Author: Takeshi KOMIYA
Author-email: i.tkomiya@gmail.com
License: BSD
Platform: any
Classifier: Development Status :: 4 - Beta
Classifier: Environment :: Console
Classifier: Environment :: Web Environment
Classifier: Intended Audience :: Developers
Classifier: License :: OSI Approved :: BSD License
Classifier: Operating System :: OS Independent
Classifier: Programming Language :: Python
Classifier: Topic :: Documentation
Classifier: Topic :: Utilities
Requires-Dist: Sphinx (>=0.6)
Requires-Dist: sphinxcontrib-imagehelper
